utils_mystuff/__init__.py
utils_mystuff/convert_regex.py
utils_mystuff/logger_CLI.py
utils_mystuff/utils_GUI.py
utils_mystuff/utils_filehandling.py
utils_mystuff/utils_various.py
utils_mystuff/version.py
utils_mystuff-1.0.1.dist-info/METADATA
utils_mystuff-1.0.1.dist-info/WHEEL
utils_mystuff-1.0.1.dist-info/licenses/AUTHORS.md
utils_mystuff-1.0.1.dist-info/licenses/LICENSE.txt
utils_mystuff-1.0.1.dist-info/RECORD
