Metadata-Version: 2.4
Name: utils-mystuff
Version: 1.0.1
Summary: Package with various utilities i.e. VB regex translation, CLI logging, file handling, basic GUI wrapper ...
Project-URL: Documentation, https://dornech.github.io/utils-mystuff
Project-URL: Source, https://github.com/dornech/utils-mystuff
Project-URL: Tracker, https://github.com/dornech/utils-mystuff/issues
Project-URL: Sponsor, https://github.com/sponsors/dornech
Author-email: dornech <dornech@gmx.de>
License: GPL-3.0-only
License-File: AUTHORS.md
License-File: LICENSE.txt
Keywords: CLI logging,GUI wrapper,RegEx conversion,command line interface,file handling,logging,regular expression
Classifier: Programming Language :: Python
Classifier: Programming Language :: Python :: 3.9
Classifier: Programming Language :: Python :: 3.10
Classifier: Programming Language :: Python :: 3.11
Classifier: Programming Language :: Python :: 3.12
Classifier: Programming Language :: Python :: 3.13
Classifier: Programming Language :: Python :: Implementation :: CPython
Requires-Python: >=3.9
Requires-Dist: easygui
Requires-Dist: freesimplegui
Requires-Dist: pymsgbox
Requires-Dist: python-dateutil
Requires-Dist: pytz
Provides-Extra: python39
Requires-Dist: typing-extensions; extra == 'python39'
